simplestatic
