Metadata-Version: 1.0
Name: django-simplestatic
Version: 0.0.5
Summary: A highly opinionated drop-in library for static file management in Django
Home-page: https://github.com/ericflo/django-simplestatic
Author: Eric Florenzano
Author-email: floguy@gmail.com
License: MIT
Platform: UNKNOWN
Classifier: Development Status :: 2 - Pre-Alpha
Classifier: Intended Audience :: Developers
Classifier: License :: OSI Approved :: MIT License
Classifier: Programming Language :: Python
Classifier: Programming Language :: Python :: 2.6
Classifier: Programming Language :: Python :: 2.7
